19 fall NIU/463 architecture/2/winans/csci463/a2/memory.v
module memory
(
	input wire [N-1:0]	din,
	input wire [N-1:0]	ain,
	input wire			we,
	output wire [N-1:0]	dout
);
	parameter N=8;
	reg [N-1:0] do_r [255:0];

	assign dout = do_r[ain];

	always @(negedge we)
	begin
		do_r[ain] <= din;
	end

endmodule

19 fall NIU/463 architecture/2/winans/csci463/a2/register.v
module register
(
	input wire [N-1:0]	din,
	input wire			we,
	input wire			reset,
	output wire [N-1:0]	dout
);
	parameter N=8;
	reg [N-1:0] do_r;

	assign dout = do_r;

	always @(posedge reset, negedge we)
	begin
		if(reset)
			do_r <= 0;
		else
			do_r <= din;
	end

endmodule

19 fall NIU/463 architecture/2/a2/mux2x1.v
module mux2x1
(
	input wire [N-1:0]	i0,
	input wire [N-1:0]	i1,
	input wire 			a,
	output wire [N-1:0]	o
);
	parameter N=8;

	always
	begin
		case(a)
		0: o = i0;
		1: o = i1;
		endcase
	end

endmodule

19 fall NIU/463 architecture/2/a2/alu1.v
module alu1
(
	input wire			ci,
	input wire			a,
	input wire			b,
	input wire			comp,
	input wire [1:0]	f,
	output wire 		co,
	output wire 		q
);
	assign co = (((b^comp)^a)&ci)|((b^comp)&a);

	always @(*)
	begin
		case (f)
		2'b00: q = ((b^comp)^a)^ci;	// adder
		2'b01: q = (b^comp)^a;		// a XOR b
		2'b10: q = a&(b^comp);		// a AND b
		2'b11: q = a|(b^comp);		// a OR b
		endcase
	end

endmodule

19 fall NIU/463 architecture/2/winans/csci463/a2/alu.v
module alu
(
	input wire			ci,
	input wire [N-1:0]	a,
	input wire [N-1:0]	b,
	input wire			comp,
	input wire [1:0]	f,
	output wire 		uo,
	output wire 		so,
	output wire [N-1:0]	q
);
	parameter N=8;

	/* verilator lint_off UNOPTFLAT */
	wire[N:0] cc;
	/* verilator lint_on UNOPTFLAT */
	assign cc[0] = ci;
	assign uo = cc[N]^(comp&ci& ~f[0] & ~f[1]);
	assign so = cc[N]^cc[N-1];

	genvar i;
	for (i=0; i<N; i=i+1)
	begin
		alu1 a_inst(.ci(cc[i]), .a(a[i]), .b(b[i]), .comp(comp), .f(f), .co(cc[i+1]), .q(q[i]));
	end

endmodule

19 fall NIU/463 architecture/2/a2/demux.v
module demux
(
	input wire [1:0]	a,
	input wire			i,
	output wire [N-1:0]	o0,
	output wire [N-1:0]	o1,
	output wire [N-1:0]	o2,
	output wire [N-1:0]	o3
);
	parameter N=1;

	always @(*)
	begin
		o0 = 0;
		o1 = 0;
		o2 = 0;
		o3 = 0;
		case(a)
		0: o0 = i;
		1: o1 = i;
		2: o2 = i;
		3: o3 = i;
		endcase
	end

endmodule

19 fall NIU/463 architecture/2/a2/mux.v
module mux
(
	input wire [N-1:0]	i0,
	input wire [N-1:0]	i1,
	input wire [N-1:0]	i2,
	input wire [N-1:0]	i3,
	input wire [1:0]	a,
	output wire [N-1:0]	o
);
	parameter N=8;

	always
	begin
		case(a)
		0: o = i0;
		1: o = i1;
		2: o = i2;
		3: o = i3;
		endcase
	end

endmodule

19 fall NIU/463 architecture/2/a2/top.v
module top
(
	input				reset,			// reset registers to 0 on rising edge
	input [1:0]			reg_addr_we,	// register address to write (on falling edge of reg_we)
	input				reg_we,			// write enable line for the register file
	input				mar_we,			// the write-enable line for the MAR
	input				mbr_out_we,		// the write-enable line for MBR_out
	input				mbr_in_we,		// the write-enable line for MBR_in
	input				mem_we,			// the write-enable line for the memory
	input				mbr_alu,		// select line for MBR/ALU mux to register input bus
	input [1:0]			alu_func,		// ALU function select
	input				alu_comp_b,		// ALU compliment b control
	input				alu_ci,			// ALU LSB carry-in
	input [1:0]			alu_reg_a,		// register address for ALU bus a
	input [1:0]			alu_reg_b,		// register address for ALU bus b
	output				alu_so,			// ALU signed overflow status
	output				alu_uo			// ALU unsigned overflow status
);
	parameter N=8;

	wire [N-1:0]	regout [3:0];		// register output busses
	wire [3:0]		regwe;				// register write-enable lines

	wire [N-1:0] alu_a;					// ALU input bus A
	wire [N-1:0] alu_b;					// ALU input bus B
	wire [N-1:0] alu_q;					// ALU output bus
	wire [N-1:0] mbr_in;				// MBR input bus
	wire [N-1:0] reg_in;				// register input bus

	wire [N-1:0] d_out;
	wire [N-1:0] d_in;
	wire [N-1:0] addr_out;

	generate
		genvar i;
		for (i=0; i<4; ++i)
		begin : register_file
			register register_inst(.din(reg_in), .we(regwe[i]), .reset(reset), .dout(regout[i]));
		end
	endgenerate

	mux amux_inst(.i0(regout[0]), .i1(regout[1]), .i2(regout[2]), .i3(regout[3]), .a(alu_reg_a), .o(alu_a));
	mux bmux_inst(.i0(regout[0]), .i1(regout[1]), .i2(regout[2]), .i3(regout[3]), .a(alu_reg_b), .o(alu_b));

	demux demux_inst(.o0(regwe[0]), .o1(regwe[1]), .o2(regwe[2]), .o3(regwe[3]), .a(reg_addr_we), .i(reg_we));

	alu alu_inst(.f(alu_func), .comp(alu_comp_b), .ci(alu_ci), .a(alu_a), .b(alu_b), .uo(alu_uo), .so(alu_so), .q(alu_q));
	mux2x1 reg_mux(.i0(alu_q), .i1(mbr_in), .a(mbr_alu), .o(reg_in));

	register umar(.din(alu_q), .we(mar_we), .reset(reset), .dout(addr_out));
	register umbr_out(.din(alu_q), .we(mbr_out_we), .reset(reset), .dout(d_out));
	register umbr_in(.din(d_in), .we(mbr_in_we), .reset(reset), .dout(mbr_in));

	memory umem(.ain(addr_out), .we(mem_we), .din(d_out), .dout(d_in));

endmodule

19 fall NIU/463 architecture/2/wave.vcd
$version Generated by VerilatedVcd $end
$date Tue Oct  8 19:46:10 2019
 $end
$timescale   1ns $end

 $scope module TOP $end
  $var wire  1 o alu_ci $end
  $var wire  1 n alu_comp_b $end
  $var wire  2 m alu_func [1:0] $end
  $var wire  2 p alu_reg_a [1:0] $end
  $var wire  2 q alu_reg_b [1:0] $end
  $var wire  1 r alu_so $end
  $var wire  1 s alu_uo $end
  $var wire  1 h mar_we $end
  $var wire  1 l mbr_alu $end
  $var wire  1 j mbr_in_we $end
  $var wire  1 i mbr_out_we $end
  $var wire  1 k mem_we $end
  $var wire  2 f reg_addr_we [1:0] $end
  $var wire  1 g reg_we $end
  $var wire  1 e reset $end
  $scope module top $end
   $var wire 32 | N [31:0] $end
   $var wire  8 ` addr_out [7:0] $end
   $var wire  8 $ alu_a [7:0] $end
   $var wire  8 % alu_b [7:0] $end
   $var wire  1 o alu_ci $end
   $var wire  1 n alu_comp_b $end
   $var wire  2 m alu_func [1:0] $end
   $var wire  8 & alu_q [7:0] $end
   $var wire  2 p alu_reg_a [1:0] $end
   $var wire  2 q alu_reg_b [1:0] $end
   $var wire  1 r alu_so $end
   $var wire  1 s alu_uo $end
   $var wire  8 Q d_in [7:0] $end
   $var wire  8 _ d_out [7:0] $end
   $var wire  1 h mar_we $end
   $var wire  1 l mbr_alu $end
   $var wire  8 ^ mbr_in [7:0] $end
   $var wire  1 j mbr_in_we $end
   $var wire  1 i mbr_out_we $end
   $var wire  1 k mem_we $end
   $var wire  2 f reg_addr_we [1:0] $end
   $var wire  8 ' reg_in [7:0] $end
   $var wire  1 g reg_we $end
   $var wire  8 R regout(0) [7:0] $end
   $var wire  8 S regout(1) [7:0] $end
   $var wire  8 T regout(2) [7:0] $end
   $var wire  8 U regout(3) [7:0] $end
   $var wire  4 # regwe [3:0] $end
   $var wire  1 e reset $end
   $scope module alu_inst $end
    $var wire 32 | N [31:0] $end
    $var wire  8 $ a [7:0] $end
    $var wire  8 % b [7:0] $end
    $var wire  9 , cc [8:0] $end
    $var wire  1 o ci $end
    $var wire  1 n comp $end
    $var wire  2 m f [1:0] $end
    $var wire  8 & q [7:0] $end
    $var wire  1 r so $end
    $var wire  1 s uo $end
    $scope module genblk1(0) $end
     $scope module a_inst $end
      $var wire  1 . a $end
      $var wire  1 / b $end
      $var wire  1 - ci $end
      $var wire  1 t co $end
      $var wire  1 n comp $end
      $var wire  2 m f [1:0] $end
      $var wire  1 0 q $end
     $upscope $end
    $upscope $end
    $scope module genblk1(1) $end
     $scope module a_inst $end
      $var wire  1 2 a $end
      $var wire  1 3 b $end
      $var wire  1 1 ci $end
      $var wire  1 u co $end
      $var wire  1 n comp $end
      $var wire  2 m f [1:0] $end
      $var wire  1 4 q $end
     $upscope $end
    $upscope $end
    $scope module genblk1(2) $end
     $scope module a_inst $end
      $var wire  1 6 a $end
      $var wire  1 7 b $end
      $var wire  1 5 ci $end
      $var wire  1 v co $end
      $var wire  1 n comp $end
      $var wire  2 m f [1:0] $end
      $var wire  1 8 q $end
     $upscope $end
    $upscope $end
    $scope module genblk1(3) $end
     $scope module a_inst $end
      $var wire  1 : a $end
      $var wire  1 ; b $end
      $var wire  1 9 ci $end
      $var wire  1 w co $end
      $var wire  1 n comp $end
      $var wire  2 m f [1:0] $end
      $var wire  1 < q $end
     $upscope $end
    $upscope $end
    $scope module genblk1(4) $end
     $scope module a_inst $end
      $var wire  1 > a $end
      $var wire  1 ? b $end
      $var wire  1 = ci $end
      $var wire  1 x co $end
      $var wire  1 n comp $end
      $var wire  2 m f [1:0] $end
      $var wire  1 @ q $end
     $upscope $end
    $upscope $end
    $scope module genblk1(5) $end
     $scope module a_inst $end
      $var wire  1 B a $end
      $var wire  1 C b $end
      $var wire  1 A ci $end
      $var wire  1 y co $end
      $var wire  1 n comp $end
      $var wire  2 m f [1:0] $end
      $var wire  1 D q $end
     $upscope $end
    $upscope $end
    $scope module genblk1(6) $end
     $scope module a_inst $end
      $var wire  1 F a $end
      $var wire  1 G b $end
      $var wire  1 E ci $end
      $var wire  1 z co $end
      $var wire  1 n comp $end
      $var wire  2 m f [1:0] $end
      $var wire  1 H q $end
     $upscope $end
    $upscope $end
    $scope module genblk1(7) $end
     $scope module a_inst $end
      $var wire  1 J a $end
      $var wire  1 K b $end
      $var wire  1 I ci $end
      $var wire  1 { co $end
      $var wire  1 n comp $end
      $var wire  2 m f [1:0] $end
      $var wire  1 L q $end
     $upscope $end
    $upscope $end
   $upscope $end
   $scope module amux_inst $end
    $var wire 32 | N [31:0] $end
    $var wire  2 p a [1:0] $end
    $var wire  8 V i0 [7:0] $end
    $var wire  8 W i1 [7:0] $end
    $var wire  8 X i2 [7:0] $end
    $var wire  8 Y i3 [7:0] $end
    $var wire  8 $ o [7:0] $end
   $upscope $end
   $scope module bmux_inst $end
    $var wire 32 | N [31:0] $end
    $var wire  2 q a [1:0] $end
    $var wire  8 Z i0 [7:0] $end
    $var wire  8 [ i1 [7:0] $end
    $var wire  8 \ i2 [7:0] $end
    $var wire  8 ] i3 [7:0] $end
    $var wire  8 % o [7:0] $end
   $upscope $end
   $scope module demux_inst $end
    $var wire 32 } N [31:0] $end
    $var wire  2 f a [1:0] $end
    $var wire  1 g i $end
    $var wire  1 ( o0 [0:0] $end
    $var wire  1 ) o1 [0:0] $end
    $var wire  1 * o2 [0:0] $end
    $var wire  1 + o3 [0:0] $end
   $upscope $end
   $scope module reg_mux $end
    $var wire 32 | N [31:0] $end
    $var wire  1 l a $end
    $var wire  8 & i0 [7:0] $end
    $var wire  8 ^ i1 [7:0] $end
    $var wire  8 ' o [7:0] $end
   $upscope $end
   $scope module register_file(0) $end
    $scope module register_inst $end
     $var wire 32 | N [31:0] $end
     $var wire  8 ' din [7:0] $end
     $var wire  8 a do_r [7:0] $end
     $var wire  8 a dout [7:0] $end
     $var wire  1 e reset $end
     $var wire  1 M we $end
    $upscope $end
   $upscope $end
   $scope module register_file(1) $end
    $scope module register_inst $end
     $var wire 32 | N [31:0] $end
     $var wire  8 ' din [7:0] $end
     $var wire  8 b do_r [7:0] $end
     $var wire  8 b dout [7:0] $end
     $var wire  1 e reset $end
     $var wire  1 N we $end
    $upscope $end
   $upscope $end
   $scope module register_file(2) $end
    $scope module register_inst $end
     $var wire 32 | N [31:0] $end
     $var wire  8 ' din [7:0] $end
     $var wire  8 c do_r [7:0] $end
     $var wire  8 c dout [7:0] $end
     $var wire  1 e reset $end
     $var wire  1 O we $end
    $upscope $end
   $upscope $end
   $scope module register_file(3) $end
    $scope module register_inst $end
     $var wire 32 | N [31:0] $end
     $var wire  8 ' din [7:0] $end
     $var wire  8 d do_r [7:0] $end
     $var wire  8 d dout [7:0] $end
     $var wire  1 e reset $end
     $var wire  1 P we $end
    $upscope $end
   $upscope $end
   $scope module umar $end
    $var wire 32 | N [31:0] $end
    $var wire  8 & din [7:0] $end
    $var wire  8 ` do_r [7:0] $end
    $var wire  8 ` dout [7:0] $end
    $var wire  1 e reset $end
    $var wire  1 h we $end
   $upscope $end
   $scope module umbr_in $end
    $var wire 32 | N [31:0] $end
    $var wire  8 Q din [7:0] $end
    $var wire  8 ^ do_r [7:0] $end
    $var wire  8 ^ dout [7:0] $end
    $var wire  1 e reset $end
    $var wire  1 j we $end
   $upscope $end
   $scope module umbr_out $end
    $var wire 32 | N [31:0] $end
    $var wire  8 & din [7:0] $end
    $var wire  8 _ do_r [7:0] $end
    $var wire  8 _ dout [7:0] $end
    $var wire  1 e reset $end
    $var wire  1 i we $end
   $upscope $end
   $scope module umem $end
    $var wire 32 | N [31:0] $end
    $var wire  8 ` ain [7:0] $end
    $var wire  8 _ din [7:0] $end
    $var wire  8 Q dout [7:0] $end
    $var wire  1 k we $end
   $upscope $end
  $upscope $end
 $upscope $end
$enddefinitions $end


#1
b0000 #
b00000000 $
b00000000 %
b00000000 &
b00000000 '
b0 (
b0 )
b0 *
b0 +
b000000000 ,
0-
0.
0/
00
01
02
03
04
05
06
07
08
09
0:
0;
0<
0=
0>
0?
0@
0A
0B
0C
0D
0E
0F
0G
0H
0I
0J
0K
0L
0M
0N
0O
0P
b10000000 Q
b00000000 R
b00000000 S
b00000000 T
b00000000 U
b00000000 V
b00000000 W
b00000000 X
b00000000 Y
b00000000 Z
b00000000 [
b00000000 \
b00000000 ]
b00000000 ^
b00000000 _
b00000000 `
b00000000 a
b00000000 b
b00000000 c
b00000000 d
0e
b00 f
0g
0h
0i
0j
0k
0l
b00 m
0n
0o
b00 p
b00 q
0r
0s
0t
0u
0v
0w
0x
0y
0z
0{
b00000000000000000000000000001000 |
b00000000000000000000000000000001 }
#2
#3
#4
#5
1e
#6
#7
#8
#9
#10
0e
#11
#12
#13
#14
#15
1j
#16
#17
#18
#19
#20
b10000000 ^
0j
#21
#22
#23
#24
#25
b0010 #
b10000000 '
b1 )
1N
b01 f
1g
1l
#26
#27
#28
#29
#30
b0000 #
b0 )
0N
b10000000 S
b10000000 W
b10000000 [
b10000000 b
0g
#31
#32
#33
#34
#35
b00000001 &
b00000001 '
b000000001 ,
1-
10
b00 f
1h
0l
1o
#36
#37
#38
#39
#40
b01000001 Q
b00000001 `
0h
#41
#42
#43
#44
#45
b00000000 &
b00000000 '
b000000000 ,
0-
00
1j
0o
#46
#47
#48
#49
#50
b01000001 ^
0j
#51
#52
#53
#54
#55
b0100 #
b01000001 '
b1 *
1O
b10 f
1g
1l
#56
#57
#58
#59
#60
b0000 #
b0 *
0O
b01000001 T
b01000001 X
b01000001 \
b01000001 c
0g
#61
#62
#63
#64
#65
b10000000 $
b10000000 &
b10000000 '
1J
1L
b00 f
1h
0l
b01 p
#66
#67
#68
#69
#70
b00000000 Q
b10000000 `
0h
#71
#72
#73
#74
#75
b01000001 $
b01000001 &
b01000001 '
1.
10
1F
1H
0J
0L
1i
b10 p
#76
#77
#78
#79
#80
b01000001 _
0i
#81
#82
#83
#84
#85
b00000000 $
b00000000 &
b00000000 '
0.
00
0F
0H
1k
b00 p
#86
#87
#88
#89
#90
b01000001 Q
0k
#91
#92
#93
#94
#95
b0010 #
b10000000 $
b10000001 &
b10000001 '
b1 )
b000000001 ,
1-
10
1J
1L
1N
b01 f
1g
1o
b01 p
#96
#97
#98
#99
#100
b0000 #
b10000001 $
b10000010 &
b10000010 '
b0 )
b000000011 ,
1.
00
11
14
0N
b10000001 S
b10000001 W
b10000001 [
b10000001 b
0g
1t
#101
#102
#103
#104
#105
b0100 #
b01000001 $
b01000010 &
b01000010 '
b1 *
1F
1H
0J
0L
1O
b10 f
1g
b10 p
#106
#107
#108
#109
#110
b0000 #
b01000010 $
b01000011 &
b01000011 '
b0 *
b000000001 ,
0.
10
01
12
0O
b01000010 T
b01000010 X
b01000010 \
b01000010 c
0g
0t
#111
#112
#113
#114
#115
b10000001 $
b10000001 &
b10000001 '
b000000000 ,
0-
1.
02
04
0F
0H
1J
1L
b00 f
1h
0o
b01 p
#116
#117
#118
#119
#120
b00000000 Q
b10000001 `
0h
#121
#122
#123
#124
#125
b01000010 $
b01000010 &
b01000010 '
0.
00
12
14
1F
1H
0J
0L
1i
b10 p
#126
#127
#128
#129
#130
b01000010 _
0i
#131
#132
#133
#134
#135
b00000000 $
b00000000 &
b00000000 '
02
04
0F
0H
1k
b00 p
#136
#137
#138
#139
#140
b01000010 Q
0k
#141
#142
#143
#144
#145
b0010 #
b10000001 $
b10000010 &
b10000010 '
b1 )
b000000011 ,
1-
1.
11
14
1J
1L
1N
b01 f
1g
1o
b01 p
1t
#146
#147
#148
#149
#150
b0000 #
b10000010 $
b10000011 &
b10000011 '
b0 )
b000000001 ,
0.
10
01
12
0N
b10000010 S
b10000010 W
b10000010 [
b10000010 b
0g
0t
#151
#152
#153
#154
#155
b0100 #
b01000010 $
b01000011 &
b01000011 '
b1 *
1F
1H
0J
0L
1O
b10 f
1g
b10 p
#156
#157
#158
#159
#160
b0000 #
b01000011 $
b01000100 &
b01000100 '
b0 *
b000000111 ,
1.
00
11
04
15
18
0O
b01000011 T
b01000011 X
b01000011 \
b01000011 c
0g
1t
1u
#161
#162
#163
#164
#165
b10000010 $
b10000010 &
b10000010 '
b000000000 ,
0-
0.
01
14
05
08
0F
0H
1J
1L
b00 f
1h
0o
b01 p
0t
0u
#166
#167
#168
#169
#170
b00000000 Q
b10000010 `
0h
#171
#172
#173
#174
#175
b01000011 $
b01000011 &
b01000011 '
1.
10
1F
1H
0J
0L
1i
b10 p
#176
#177
#178
#179
#180
b01000011 _
0i
#181
#182
#183
#184
#185
b00000000 $
b00000000 &
b00000000 '
0.
00
02
04
0F
0H
1k
b00 p
#186
#187
#188
#189
#190
b01000011 Q
0k
#191
#192
#193
#194
#195
b0010 #
b10000010 $
b10000011 &
b10000011 '
b1 )
b000000001 ,
1-
10
12
14
1J
1L
1N
b01 f
1g
1o
b01 p
#196
#197
#198
#199
#200
b0000 #
b10000011 $
b10000100 &
b10000100 '
b0 )
b000000111 ,
1.
00
11
04
15
18
0N
b10000011 S
b10000011 W
b10000011 [
b10000011 b
0g
1t
1u
#201
#202
#203
#204
#205
b0100 #
b01000011 $
b01000100 &
b01000100 '
b1 *
1F
1H
0J
0L
1O
b10 f
1g
b10 p
#206
#207
#208
#209
#210
b0000 #
b01000100 $
b01000101 &
b01000101 '
b0 *
b000000001 ,
0.
10
01
02
05
16
0O
b01000100 T
b01000100 X
b01000100 \
b01000100 c
0g
0t
0u
#211
#212
#213
#214
#215
b10000011 $
b10000011 &
b10000011 '
b000000000 ,
0-
1.
12
14
06
08
0F
0H
1J
1L
b00 f
1h
0o
b01 p
#216
#217
#218
#219
#220
b00000000 Q
b10000011 `
0h
#221
#222
#223
#224
#225
b01000100 $
b01000100 &
b01000100 '
0.
00
02
04
16
18
1F
1H
0J
0L
1i
b10 p
#226
#227
#228
#229
#230
b01000100 _
0i
#231
#232
#233
#234
#235
b00000000 $
b00000000 &
b00000000 '
06
08
0F
0H
1k
b00 p
#236
#237
#238
#239
#240
b01000100 Q
0k
#241
#242
#243
#244
#245
b0010 #
b10000011 $
b10000100 &
b10000100 '
b1 )
b000000111 ,
1-
1.
11
12
15
18
1J
1L
1N
b01 f
1g
1o
b01 p
1t
1u
#246
#247
#248
#249
#250
b0000 #
b10000100 $
b10000101 &
b10000101 '
b0 )
b000000001 ,
0.
10
01
02
05
16
0N
b10000100 S
b10000100 W
b10000100 [
b10000100 b
0g
0t
0u
#251
#252
#253
#254
#255
b0100 #
b01000100 $
b01000101 &
b01000101 '
b1 *
1F
1H
0J
0L
1O
b10 f
1g
b10 p
#256
#257
#258
#259
#260
b0000 #
b01000101 $
b01000110 &
b01000110 '
b0 *
b000000011 ,
1.
00
11
14
0O
b01000101 T
b01000101 X
b01000101 \
b01000101 c
0g
1t
#261
#262
#263
#264
#265
b10000100 $
b10000100 &
b10000100 '
b000000000 ,
0-
0.
01
04
0F
0H
1J
1L
b00 f
1h
0o
b01 p
0t
#266
#267
#268
#269
#270
b00000000 Q
b10000100 `
0h
#271
#272
#273
#274
#275
b01000101 $
b01000101 &
b01000101 '
1.
10
1F
1H
0J
0L
1i
b10 p
#276
#277
#278
#279
#280
b01000101 _
0i
#281
#282
#283
#284
#285
b00000000 $
b00000000 &
b00000000 '
0.
00
06
08
0F
0H
1k
b00 p
#286
#287
#288
#289
#290
b01000101 Q
0k
#291
#292
#293
#294
#295
b0010 #
b10000100 $
b10000101 &
b10000101 '
b1 )
b000000001 ,
1-
10
16
18
1J
1L
1N
b01 f
1g
1o
b01 p
#296
#297
#298
#299
#300
b0000 #
b10000101 $
b10000110 &
b10000110 '
b0 )
b000000011 ,
1.
00
11
14
0N
b10000101 S
b10000101 W
b10000101 [
b10000101 b
0g
1t
#301
#302
#303
#304
#305
b0100 #
b01000101 $
b01000110 &
b01000110 '
b1 *
1F
1H
0J
0L
1O
b10 f
1g
b10 p
#306
#307
#308
#309
#310
b0000 #
b01000110 $
b01000111 &
b01000111 '
b0 *
b000000001 ,
0.
10
01
12
0O
b01000110 T
b01000110 X
b01000110 \
b01000110 c
0g
0t
#311
#312
#313
#314
#315
b10000101 $
b10000101 &
b10000101 '
b000000000 ,
0-
1.
02
04
0F
0H
1J
1L
b00 f
1h
0o
b01 p
#316
#317
#318
#319
#320
b00000000 Q
b10000101 `
0h
#321
#322
#323
#324
#325
b01000110 $
b01000110 &
b01000110 '
0.
00
12
14
1F
1H
0J
0L
1i
b10 p
#326
#327
#328
#329
#330
b01000110 _
0i
#331
#332
#333
#334
#335
b00000000 $
b00000000 &
b00000000 '
02
04
06
08
0F
0H
1k
b00 p
#336
#337
#338
#339
#340
b01000110 Q
0k
#341
#342
#343
#344
#345
b0010 #
b10000101 $
b10000110 &
b10000110 '
b1 )
b000000011 ,
1-
1.
11
14
16
18
1J
1L
1N
b01 f
1g
1o
b01 p
1t
#346
#347
#348
#349
#350
b0000 #
b10000110 $
b10000111 &
b10000111 '
b0 )
b000000001 ,
0.
10
01
12
0N
b10000110 S
b10000110 W
b10000110 [
b10000110 b
0g
0t
#351
#352
#353
#354
#355
b0100 #
b01000110 $
b01000111 &
b01000111 '
b1 *
1F
1H
0J
0L
1O
b10 f
1g
b10 p
#356
#357
#358
#359
#360
b0000 #
b01000111 $
b01001000 &
b01001000 '
b0 *
b000001111 ,
1.
00
11
04
15
08
19
1<
0O
b01000111 T
b01000111 X
b01000111 \
b01000111 c
0g
1t
1u
1v
#361
#362
#363
#364
#365
b10000110 $
b10000110 &
b10000110 '
b000000000 ,
0-
0.
01
14
05
18
09
0<
0F
0H
1J
1L
b00 f
1h
0o
b01 p
0t
0u
0v
#366
#367
#368
#369
#370
b00000000 Q
b10000110 `
0h
#371
#372
#373
#374
#375
b01000111 $
b01000111 &
b01000111 '
1.
10
1F
1H
0J
0L
1i
b10 p
#376
#377
#378
#379
#380
b01000111 _
0i
#381
#382
#383
#384
#385
b00000000 $
b00000000 &
b00000000 '
0.
00
02
04
06
08
0F
0H
1k
b00 p
#386
#387
#388
#389
#390
b01000111 Q
0k
#391
#392
#393
#394
#395
b0010 #
b10000110 $
b10000111 &
b10000111 '
b1 )
b000000001 ,
1-
10
12
14
16
18
1J
1L
1N
b01 f
1g
1o
b01 p
#396
#397
#398
#399
#400
b0000 #
b10000111 $
b10001000 &
b10001000 '
b0 )
b000001111 ,
1.
00
11
04
15
08
19
1<
0N
b10000111 S
b10000111 W
b10000111 [
b10000111 b
0g
1t
1u
1v
#401
#402
#403
#404
#405
b0100 #
b01000111 $
b01001000 &
b01001000 '
b1 *
1F
1H
0J
0L
1O
b10 f
1g
b10 p
#406
#407
#408
#409
#410
b0000 #
b01001000 $
b01001001 &
b01001001 '
b0 *
b000000001 ,
0.
10
01
02
05
06
09
1:
0O
b01001000 T
b01001000 X
b01001000 \
b01001000 c
0g
0t
0u
0v
#411
#412
#413
#414
#415
b10000111 $
b10000111 &
b10000111 '
b000000000 ,
0-
1.
12
14
16
18
0:
0<
0F
0H
1J
1L
b00 f
1h
0o
b01 p
#416
#417
#418
#419
#420
b00000000 Q
b10000111 `
0h
#421
#422
#423
#424
#425
b01001000 $
b01001000 &
b01001000 '
0.
00
02
04
06
08
1:
1<
1F
1H
0J
0L
1i
b10 p
#426
#427
#428
#429
#430
b01001000 _
0i
#431
#432
#433
#434
#435
b00000000 $
b00000000 &
b00000000 '
0:
0<
0F
0H
1k
b00 p
#436
#437
#438
#439
#440
b01001000 Q
0k
